middle/__init__.py
middle/config.py
middle/converters.py
middle/dispatch.py
middle/dtutils.py
middle/exceptions.py
middle/formats.py
middle/model.py
middle/options.py
middle/values.py
middle/compat/__init__.py
middle/compat/types.py
middle/validators/__init__.py
middle/validators/base_validator.py
middle/validators/dicts.py
middle/validators/lists.py
middle/validators/numbers.py
middle/validators/rules.py
middle/validators/strings.py
middle-0.2.4.dist-info/AUTHORS.rst
middle-0.2.4.dist-info/LICENSE
middle-0.2.4.dist-info/METADATA
middle-0.2.4.dist-info/WHEEL
middle-0.2.4.dist-info/top_level.txt
middle-0.2.4.dist-info/RECORD
