Metadata-Version: 1.1
Name: middle
Version: 0.2.4
Summary: Flexible, extensible Python data structures for general usage
Home-page: https://github.com/vltr/middle
Author: Richard Kuesters
Author-email: rkuesters@gmail.com
License: MIT license
Keywords: attrs,object,primitives,serialization,models,hooks,customizable,utilities
Platform: UNKNOWN
Classifier: Development Status :: 3 - Alpha
Classifier: Intended Audience :: Developers
Classifier: License :: OSI Approved :: MIT License
Classifier: Operating System :: Unix
Classifier: Operating System :: POSIX
Classifier: Operating System :: Microsoft :: Windows
Classifier: Programming Language :: Python
Classifier: Programming Language :: Python :: 3.5
Classifier: Programming Language :: Python :: 3.6
Classifier: Programming Language :: Python :: 3.7
Classifier: Programming Language :: Python :: Implementation :: CPython
Classifier: Topic :: Utilities
